tw2gif/__init__.py
tw2gif/settings.py
tw2gif/tw2gif.py
tw2gif/scripts/video_to_gif.sh
tw2gif-0.0.1.dev0.data/data/tw2gif/scripts/video_to_gif.sh
tw2gif-0.0.1.dev0.dist-info/DESCRIPTION.rst
tw2gif-0.0.1.dev0.dist-info/METADATA
tw2gif-0.0.1.dev0.dist-info/RECORD
tw2gif-0.0.1.dev0.dist-info/WHEEL
tw2gif-0.0.1.dev0.dist-info/entry_points.txt
tw2gif-0.0.1.dev0.dist-info/metadata.json
tw2gif-0.0.1.dev0.dist-info/top_level.txt
