Metadata-Version: 2.0
Name: tw2gif
Version: 0.0.1.dev0
Summary: Download GIF from twitter via command line!
Home-page: https://github.com/pablo-moreno/tw2gif
Author: Pablo Moreno
Author-email: pablomoreno.inf@gmail.com
License: MIT
Keywords: twitter gif cli
Platform: UNKNOWN
Classifier: Development Status :: 3 - Alpha
Classifier: Intended Audience :: Developers
Classifier: Topic :: Software Development :: Build Tools
Classifier: License :: OSI Approved :: MIT License
Classifier: Operating System :: OS Independent
Classifier: Programming Language :: Python :: 3.5
Classifier: Programming Language :: Python :: 3.6
Requires-Dist: click
Requires-Dist: python-twitter
Provides-Extra: dev
Requires-Dist: check-manifest; extra == 'dev'
Provides-Extra: test
Requires-Dist: coverage; extra == 'test'
